src/main.py
bg_myproject-0.2.0.dist-info/METADATA
bg_myproject-0.2.0.dist-info/WHEEL
bg_myproject-0.2.0.dist-info/licenses/LICENSE
bg_myproject-0.2.0.dist-info/RECORD
