Metadata-Version: 2.4
Name: bg-myproject
Version: 0.2.0
License-File: LICENSE
Requires-Python: >=3.10
Provides-Extra: all
Requires-Dist: bgoptimizer; extra == 'all'
Requires-Dist: bgtrainer; extra == 'all'
Provides-Extra: bgoptimizer
Requires-Dist: bgoptimizer>=0.2.0; extra == 'bgoptimizer'
Provides-Extra: bgtrainer
Requires-Dist: bgtrainer>=0.2.0; extra == 'bgtrainer'
